Metadata-Version: 2.1
Name: rxn-opennmt-py
Version: 1.1.5
Summary: Fork of OpenNMT-py for use in RXN projects
Project-URL: Documentation, http://opennmt.net/OpenNMT-py/
Project-URL: Source, https://github.com/rxn4chemistry/OpenNMT-py/
License-File: LICENSE.md
Requires-Dist: six
Requires-Dist: tqdm
Requires-Dist: torch <1.6,>=1.2
Requires-Dist: torchtext ==0.4.0
Requires-Dist: future
Requires-Dist: configargparse
